{
  "attributes": {
    "description": "",
    "kibanaSavedObjectMeta": {
      "searchSourceJSON": "{\"query\":{\"query\":\"\",\"language\":\"kuery\"},\"filter\":[],\"indexRefName\":\"kibanaSavedObjectMeta.searchSourceJSON.index\"}"
    },
    "title": "response-body-bytes",
    "uiStateJSON": "{}",
    "version": 1,
    "visState": "{\"title\":\"response-body-bytes\",\"type\":\"area\",\"aggs\":[{\"id\":\"1\",\"enabled\":true,\"type\":\"sum\",\"params\":{\"field\":\"http.response.body.bytes\"},\"schema\":\"metric\"},{\"id\":\"2\",\"enabled\":true,\"type\":\"date_histogram\",\"params\":{\"field\":\"@timestamp\",\"timeRange\":{\"from\":\"now-12h\",\"to\":\"now\"},\"useNormalizedEsInterval\":true,\"scaleMetricValues\":false,\"interval\":\"auto\",\"drop_partials\":false,\"min_doc_count\":1,\"extended_bounds\":{}},\"schema\":\"segment\"},{\"id\":\"4\",\"enabled\":true,\"type\":\"count\",\"params\":{},\"schema\":\"radius\"},{\"id\":\"5\",\"enabled\":true,\"type\":\"avg\",\"params\":{\"field\":\"http.response.body.bytes\"},\"schema\":\"metric\"}],\"params\":{\"type\":\"area\",\"grid\":{\"categoryLines\":false},\"categoryAxes\":[{\"id\":\"CategoryAxis-1\",\"type\":\"category\",\"position\":\"bottom\",\"show\":true,\"style\":{},\"scale\":{\"type\":\"linear\"},\"labels\":{\"show\":true,\"filter\":true,\"truncate\":100},\"title\":{}}],\"valueAxes\":[{\"id\":\"ValueAxis-1\",\"name\":\"LeftAxis-1\",\"type\":\"value\",\"position\":\"left\",\"show\":true,\"style\":{},\"scale\":{\"type\":\"linear\",\"mode\":\"normal\"},\"labels\":{\"show\":true,\"rotate\":0,\"filter\":false,\"truncate\":100},\"title\":{\"text\":\"Sum of http.response.body.bytes\"}},{\"id\":\"ValueAxis-2\",\"name\":\"RightAxis-1\",\"type\":\"value\",\"position\":\"right\",\"show\":true,\"style\":{},\"scale\":{\"type\":\"linear\",\"mode\":\"normal\"},\"labels\":{\"show\":true,\"rotate\":0,\"filter\":false,\"truncate\":100},\"title\":{\"text\":\"Average http.response.body.bytes\"}}],\"seriesParams\":[{\"show\":true,\"type\":\"area\",\"mode\":\"normal\",\"data\":{\"label\":\"Sum of http.response.body.bytes\",\"id\":\"1\"},\"drawLinesBetweenPoints\":true,\"lineWidth\":2,\"showCircles\":true,\"interpolate\":\"linear\",\"valueAxis\":\"ValueAxis-1\"},{\"show\":true,\"type\":\"area\",\"mode\":\"stacked\",\"data\":{\"id\":\"5\",\"label\":\"Average http.response.body.bytes\"},\"drawLinesBetweenPoints\":true,\"lineWidth\":2,\"showCircles\":true,\"interpolate\":\"linear\",\"valueAxis\":\"ValueAxis-2\"}],\"addTooltip\":true,\"addLegend\":true,\"legendPosition\":\"right\",\"times\":[],\"addTimeMarker\":false,\"thresholdLine\":{\"show\":false,\"value\":10,\"width\":1,\"style\":\"full\",\"color\":\"#E7664C\"},\"labels\":{},\"radiusRatio\":50}}"
  },
  "id": "68040070-f064-11ea-8a36-c5c24b329c44",
  "migrationVersion": {
    "visualization": "7.8.0"
  },
  "references": [
    {
      "id": "74f6ddc0-f05a-11ea-8a36-c5c24b329c44",
      "name": "kibanaSavedObjectMeta.searchSourceJSON.index",
      "type": "index-pattern"
    }
  ],
  "type": "visualization",
  "updated_at": "2020-09-06T17:14:22.070Z",
  "version": "WzYxMywxXQ=="
}